{
  "feature1": {
    "explanation": "Both texts use punctuation marks consistently and appropriately, including hyphens, parentheses, and commas.",
    "score": 0.8
  },
  "feature2": {
    "explanation": "Both texts exhibit similar lexical choices and word usage. The sentence structures are also relatively similar.",
    "score": 0.7
  },
  "feature3": {
    "explanation": "The texts show coherence and cohesion in their structure. The sentence complexity and length are not significantly different.",
    "score": 0.6
  },
  "feature4": {
    "explanation": "Both texts share a similar informal tone and mood. They both involve recounting events or expressing opinions.",
    "score": 0.9
  },
  "feature5": {
    "explanation": "There are no noticeable spelling or typographical errors in either text.",
    "score": 1.0
  },
  "overall": {
    "explanation": "Considering the overall similarity in punctuation style, lexical and grammatical features, coherence, tone, and absence of spelling errors, the likelihood of the texts being written by the same author is moderately high.",
    "score": 0.8
  }
}