{
    "feature1": {
        "explanation": "Both texts show consistent use of hyphens, commas, and parentheses, though not extensively used in either text.",
        "score": 0.6
    },
    "feature2": {
        "explanation": "Lexical and grammatical features show some similarities in terms of vocabulary choice and sentence structures.",
        "score": 0.5
    },
    "feature3": {
        "explanation": "Sentence structures differ with varying complexity and length in the texts. Text coherence and cohesion show inconsistencies.",
        "score": 0.4
    },
    "feature4": {
        "explanation": "Narrative styles, tone, and mood differ significantly between the two texts.",
        "score": 0.3
    },
    "feature5": {
        "explanation": "No spelling or typographical errors were identified in either text.",
        "score": 1.0
    },
    "overall": {
        "explanation": "The texts exhibit moderate similarities in punctuation style and lexical features, but significant differences in sentence structure, discourse features, and tone. The lack of spelling errors adds to the overall assessment.",
        "score": 0.56
    }
}