{
  "feature1": {
    "explanation": "Both texts exhibit similar punctuation usage with colons, commas, and parentheses being used in a structured manner.",
    "score": 0.8
  },
  "feature2": {
    "explanation": "There is consistency in lexical and grammatical features such as word choice and grammatical categories.",
    "score": 0.7
  },
  "feature3": {
    "explanation": "While both texts have different structural characteristics, they maintain coherence and cohesion in their respective contexts.",
    "score": 0.6
  },
  "feature4": {
    "explanation": "The narrative styles and speech events differ between the texts, leading to a lower score in this feature.",
    "score": 0.4
  },
  "feature5": {
    "explanation": "There are no spelling or typographical errors in either text.",
    "score": 1
  },
  "overall": {
    "explanation": "Overall, considering the commonalities and distinctions in the features analyzed, there is a moderate confidence level that the two texts were written by the same author.",
    "score": 0.7
  }
}