{
  "feature1": {
    "explanation": "Both texts demonstrate consistent use of punctuation marks like colons and commas.",
    "score": 0.8
  },
  "feature2": {
    "explanation": "Both texts exhibit similar lexical and grammatical features in terms of formal language usage.",
    "score": 0.7
  },
  "feature3": {
    "explanation": "Both texts maintain a similar level of sentence complexity and coherence.",
    "score": 0.6
  },
  "feature4": {
    "explanation": "The texts differ significantly in content and tone, which may suggest different authors.",
    "score": 0.3
  },
  "feature5": {
    "explanation": "There are no noticeable spelling or typographical errors in either text.",
    "score": 1.0
  },
  "overall": {
    "explanation": "Considering the overall assessment of the linguistic features, there is moderate evidence to suggest that the two texts may have been written by different authors due to differences in content and tone.",
    "score": 0.68
  }
}