{
  "feature1": {
    "explanation": "Both texts demonstrate consistent use of commas to separate clauses and phrases.",
    "score": 0.8
  },
  "feature2": {
    "explanation": "Both texts exhibit a similar level of lexical variation and word choice with a focus on geopolitical terms and military context.",
    "score": 0.7
  },
  "feature3": {
    "explanation": "The texts share similarities in sentence structure, coherence, and word frequency.",
    "score": 0.75
  },
  "feature4": {
    "explanation": "Both texts maintain a serious and analytical tone in discussing the geopolitical situation.",
    "score": 0.85
  },
  "feature5": {
    "explanation": "There are no spelling or typographical errors in either text.",
    "score": 1
  },
  "overall": {
    "explanation": "Considering the consistent use of punctuation, lexical choices, sentence structure, tone, and absence of errors, there is a moderate likelihood that the two texts were written by the same author.",
    "score": 0.8
  }
}