{
  "feature1": {
    "explanation": "Both texts exhibit consistent use of punctuation marks such as colons, commas, and parentheses.",
    "score": 0.8
  },
  "feature2": {
    "explanation": "Both texts maintain similar lexical and grammatical features in terms of word choice and sentence structures.",
    "score": 0.7
  },
  "feature3": {
    "explanation": "The sentence structures in both texts are coherent and relatively similar in length and complexity.",
    "score": 0.6
  },
  "feature4": {
    "explanation": "The narrative styles and tone are different due to the topics discussed, but there are some common expressions used.",
    "score": 0.4
  },
  "feature5": {
    "explanation": "No spelling or typographical errors were found in either text.",
    "score": 1
  },
  "overall": {
    "explanation": "Considering the commonalities in punctuation, lexical and grammatical features, and absence of spelling errors, there is a moderate likelihood that the two texts were written by the same author.",
    "score": 0.7
  }
}