{
    "feature1": {
        "explanation": "Both texts use consistent punctuation styles including quotation marks and ellipses.",
        "score": 0.85
    },
    "feature2": {
        "explanation": "Similar lexical and grammatical features observed with common word choices and sentence structures.",
        "score": 0.80
    },
    "feature3": {
        "explanation": "Both texts exhibit comparable sentence structures and lengths, maintaining coherence in expression.",
        "score": 0.75
    },
    "feature4": {
        "explanation": "The narrative styles and tone are somewhat similar, focusing on conveying personal opinions and reflections.",
        "score": 0.70
    },
    "feature5": {
        "explanation": "No spelling or typographical errors were noted in either text.",
        "score": 1.0
    },
    "overall": {
        "explanation": "Considering the combination of punctuation style, lexical and grammatical features, sentence structure, text discourse, and absence of errors, there is a high likelihood that the two texts were written by the same author.",
        "score": 0.82
    }
}