{
    "feature1": {
        "explanation": "Both texts use hyphens, parentheses, and commas for punctuation, displaying a similar style.",
        "score": 0.8
    },
    "feature2": {
        "explanation": "The lexical and grammatical features in both texts show similarities in word choice and grammatical structures.",
        "score": 0.7
    },
    "feature3": {
        "explanation": "Both texts exhibit similar sentence structures and coherence, with a consistent level of complexity.",
        "score": 0.75
    },
    "feature4": {
        "explanation": "The tone and mood in both texts are somewhat distinct, with one showing frustration and the other a more speculative tone.",
        "score": 0.5
    },
    "feature5": {
        "explanation": "Both texts are free of spelling and typographical errors.",
        "score": 1
    },
    "overall": {
        "explanation": "Considering the overall assessment of the linguistic features, there is a moderate level of confidence that the texts were written by the same author.",
        "score": 0.75
    }
}