{
  "feature1": {
    "explanation": "Both texts use quotation marks, commas, and periods consistently.",
    "score": 0.8
  },
  "feature2": {
    "explanation": "Both texts exhibit a similar level of formality in word choice and grammatical structure.",
    "score": 0.7
  },
  "feature3": {
    "explanation": "Paragraph 1 has shorter sentences with a more direct tone, while Paragraph 2 includes longer sentences with guidelines and rules.",
    "score": 0.5
  },
  "feature4": {
    "explanation": "Paragraph 1 has a more critical and informal tone, while Paragraph 2 is more formal and instructional.",
    "score": 0.6
  },
  "feature5": {
    "explanation": "There are no noticeable spelling or typographical errors in either text.",
    "score": 1
  },
  "overall": {
    "explanation": "Considering all the features, there are similarities in punctuation, lexical features, and lack of errors, but differences in sentence structure, tone, and discourse style.",
    "score": 0.72
  }
}