{
  "feature1": {
    "explanation": "Both texts use hyphens and ellipses for punctuation.",
    "score": 0.8
  },
  "feature2": {
    "explanation": "Text 1 uses more formal language related to trade and tariffs, while Text 2 has a more casual tone discussing car sales.",
    "score": 0.4
  },
  "feature3": {
    "explanation": "Both texts are relatively short with straightforward sentence structures.",
    "score": 0.6
  },
  "feature4": {
    "explanation": "Text 1 has a serious and informative tone, while Text 2 has a more casual and humorous tone.",
    "score": 0.3
  },
  "feature5": {
    "explanation": "Both texts are free from spelling and typographical errors.",
    "score": 1
  },
  "overall": {
    "explanation": "Based on the analysis of punctuation, sentence structure, and spelling, there are some commonalities that suggest a moderate likelihood of the same author, but differences in tone and content lower the overall confidence score.",
    "score": 0.62
  }
}