{
  "feature1": {
    "explanation": "Both texts show consistent use of hyphens, commas, and colons for punctuation.",
    "score": 0.8
  },
  "feature2": {
    "explanation": "Both texts exhibit similar lexical and grammatical features with a mix of complex and simple language structures.",
    "score": 0.7
  },
  "feature3": {
    "explanation": "The sentence structures in both texts are coherent and exhibit a mix of sentence lengths.",
    "score": 0.85
  },
  "feature4": {
    "explanation": "Both texts have a serious tone and discuss societal issues.",
    "score": 0.9
  },
  "feature5": {
    "explanation": "There are no spelling or typographical errors in either text.",
    "score": 1
  },
  "overall": {
    "explanation": "Overall, considering the commonalities in punctuation, lexical and grammatical features, sentence structure, tone, and absence of spelling errors, there is a moderate to high likelihood that the two texts were written by the same author.",
    "score": 0.85
  }
}