{
  "feature1": {
    "explanation": "Both texts exhibit consistent use of punctuation such as commas and periods to separate clauses and sentences.",
    "score": 0.8
  },
  "feature2": {
    "explanation": "There are similarities in lexical choices and grammatical structures, indicating a potential overlap in writing style.",
    "score": 0.7
  },
  "feature3": {
    "explanation": "Both texts display a mix of sentence lengths and structures, contributing to a moderate level of similarity.",
    "score": 0.6
  },
  "feature4": {
    "explanation": "While the narrative events differ, the tone and mood in both texts are informative and factual, showing some consistency.",
    "score": 0.6
  },
  "feature5": {
    "explanation": "No spelling or typographical errors were observed in either text.",
    "score": 1
  },
  "overall": {
    "explanation": "Considering the analysis of punctuation style, lexical and grammatical features, sentence structure, text and discourse features, and spelling accuracy, the likelihood that the two texts were written by the same author is moderately high.",
    "score": 0.74
  }
}