{
    "feature1": {
        "explanation": "Both texts exhibit consistent use of commas and periods for punctuation.",
        "score": 0.8
    },
    "feature2": {
        "explanation": "Both texts show similarity in lexical choices and word usage, despite differences in content.",
        "score": 0.7
    },
    "feature3": {
        "explanation": "The sentence structures in both texts are relatively simple and direct, with a similar level of coherence.",
        "score": 0.6
    },
    "feature4": {
        "explanation": "The tone and mood in both texts are somewhat different - one is more informative while the other is speculative and negative.",
        "score": 0.4
    },
    "feature5": {
        "explanation": "No significant spelling or typographical errors were observed in either text.",
        "score": 0.9
    },
    "overall": {
        "explanation": "Considering the overall assessment of the five features, the likelihood that the two texts were written by the same author is moderate.",
        "score": 0.68
    }
}