{
  "feature1": {
    "explanation": "Both texts use hyphens, colons, commas, and quotation marks in a similar manner for punctuation.",
    "score": 0.9
  },
  "feature2": {
    "explanation": "There are differences in lexical and grammatical features, with distinct word choices and sentence structures between the two texts.",
    "score": 0.4
  },
  "feature3": {
    "explanation": "The sentence structures and quantitative features differ significantly in complexity, length, and arrangement.",
    "score": 0.3
  },
  "feature4": {
    "explanation": "The narrative styles, speech events, and tone are distinct in each text, indicating different writing styles.",
    "score": 0.2
  },
  "feature5": {
    "explanation": "There are no spelling or typographical errors observed in either text.",
    "score": 1
  },
  "overall": {
    "explanation": "Considering the analysis of punctuation style, lexical and grammatical features, sentence structure, text and discourse features, and spelling errors, the overall likelihood of the two texts being written by the same author is low.",
    "score": 0.56
  }
}