{
    "feature1": {
        "explanation": "Both texts use punctuation marks such as question marks, exclamation marks, commas, and periods similarly.",
        "score": 0.8
    },
    "feature2": {
        "explanation": "Both texts exhibit a mix of formal and informal language, with differences in tone and word choice.",
        "score": 0.5
    },
    "feature3": {
        "explanation": "The sentence structures vary, with one text having a more informal and fragmented structure compared to the other.",
        "score": 0.6
    },
    "feature4": {
        "explanation": "The narrative styles differ significantly; one text is more confrontational and critical, while the other is nostalgic and appreciative.",
        "score": 0.4
    },
    "feature5": {
        "explanation": "There are no spelling or typographical errors present in either text.",
        "score": 1
    },
    "overall": {
        "explanation": "Overall, considering the differences in tone, narrative style, and word choice, the likelihood of the two texts being written by the same author is low.",
        "score": 0.66
    }
}