{
  "feature1": {
    "explanation": "Both texts use ellipses (...) and quotation marks in a similar manner.",
    "score": 0.8
  },
  "feature2": {
    "explanation": "Both texts exhibit a similar level of formality in word choice and grammatical structures.",
    "score": 0.7
  },
  "feature3": {
    "explanation": "The sentence structures in both texts are moderately complex and show coherence.",
    "score": 0.6
  },
  "feature4": {
    "explanation": "Both texts share a similar serious and informative tone, with no distinctive narrative styles.",
    "score": 0.7
  },
  "feature5": {
    "explanation": "There are no spelling or typographical errors in either text.",
    "score": 1.0
  },
  "overall": {
    "explanation": "Considering the commonalities in punctuation style, lexical features, coherence, tone, and absence of errors, the likelihood that the texts were written by the same author is moderately high.",
    "score": 0.76
  }
}